<?xml version="1.0"?>
<psalm
    xmlns:xsi="http://www.w3.org/2001/XMLSchema-instance"
    xmlns="https://getpsalm.org/schema/config"
    xsi:schemaLocation="https://getpsalm.org/schema/config vendor/vimeo/psalm/config.xsd"
    errorLevel="8"
    resolveFromConfigFile="true"
    findUnusedBaselineEntry="true"
    findUnusedCode="true"
    findUnusedVariablesAndParams="true"
>
    <projectFiles>
        <directory name="src" />
        <directory name="tests" />
        <ignoreFiles>
            <directory name="vendor" />
        </ignoreFiles>
    </projectFiles>

    <issueHandlers>
        <LessSpecificReturnType errorLevel="info" />
        <MoreSpecificReturnType errorLevel="info" />
        <PossiblyUndefinedMethod errorLevel="info" />
        <PossiblyUndefinedVariable errorLevel="info" />
        <PossiblyUndefinedIntArrayOffset errorLevel="info" />
        <PossiblyUndefinedStringArrayOffset errorLevel="info" />
        <PossiblyUndefinedPropertyAssignment errorLevel="info" />
        <PossiblyUndefinedPropertyFetch errorLevel="info" />
        <PossiblyInvalidArgument errorLevel="info" />
        <PossiblyInvalidCast errorLevel="info" />
        <PossiblyInvalidIterator errorLevel="info" />
        <PossiblyInvalidArrayAccess errorLevel="info" />
        <PossiblyInvalidArrayAssignment errorLevel="info" />
        <PossiblyInvalidArrayOffset errorLevel="info" />
        <PossiblyInvalidPropertyAssignment errorLevel="info" />
        <PossiblyInvalidPropertyFetch errorLevel="info" />
        <PossiblyInvalidMethodCall errorLevel="info" />
        <PossiblyNullReference errorLevel="info" />
        <PossiblyNullPropertyAssignment errorLevel="info" />
        <PossiblyNullPropertyFetch errorLevel="info" />
        <PossiblyNullArrayAccess errorLevel="info" />
        <PossiblyNullArrayAssignment errorLevel="info" />
        <PossiblyNullArrayOffset errorLevel="info" />
        <PossiblyNullIterator errorLevel="info" />
        <PossiblyNullFunctionCall errorLevel="info" />
        <PossiblyNullOperand errorLevel="info" />
        <PossiblyNullArgument errorLevel="info" />
        <PossiblyNullArrayAccess errorLevel="info" />
        <PossiblyNullPropertyAssignment errorLevel="info" />
        <PossiblyNullPropertyFetch errorLevel="info" />
        <NullReference errorLevel="info" />
        <UndefinedThisPropertyAssignment errorLevel="info" />
        <UndefinedThisPropertyFetch errorLevel="info" />
        <UndefinedMethod errorLevel="info" />
        <UndefinedFunction errorLevel="info" />
        <UndefinedVariable errorLevel="info" />
        <UndefinedClass errorLevel="info" />
        <UndefinedGlobalVariable errorLevel="info" />
        <UndefinedConstant errorLevel="info" />
        <UndefinedPropertyAssignment errorLevel="info" />
        <UndefinedPropertyFetch errorLevel="info" />
        <InvalidScalarArgument errorLevel="info" />
        <InvalidArgument errorLevel="info" />
        <InvalidCast errorLevel="info" />
        <InvalidIterator errorLevel="info" />
        <InvalidArrayAccess errorLevel="info" />
        <InvalidArrayAssignment errorLevel="info" />
        <InvalidArrayOffset errorLevel="info" />
        <InvalidPropertyAssignment errorLevel="info" />
        <InvalidPropertyFetch errorLevel="info" />
        <InvalidMethodCall errorLevel="info" />
        <InvalidReturnType errorLevel="info" />
        <InvalidStringClass errorLevel="info" />
        <InvalidFalsableReturnType errorLevel="info" />
        <InvalidNullableReturnType errorLevel="info" />
        <InvalidOperand errorLevel="info" />
        <NoInterfaceProperties errorLevel="info" />
        <MissingClosureReturnType errorLevel="info" />
        <MissingReturnType errorLevel="info" />
        <MissingParamType errorLevel="info" />
        <MissingPropertyType errorLevel="info" />
        <MissingClosureParamType errorLevel="info" />
        <ImplicitToStringCast errorLevel="info" />
        <RedundantCondition errorLevel="info" />
        <RedundantConditionGivenDocblockType errorLevel="info" />
        <RedundantFunctionCallGivenDocblockType errorLevel="info" />
        <RedundantPropertyInitializationCheck errorLevel="info" />
        <RedundantCast errorLevel="info" />
        <RedundantCastGivenDocblockType errorLevel="info" />
        <DocblockTypeContradiction errorLevel="info" />
        <TypeDoesNotContainType errorLevel="info" />
        <TypeDoesNotContainNull errorLevel="info" />
        <RedundantConditionGivenDocblockType errorLevel="info" />
        <ParadoxicalCondition errorLevel="info" />
        <FalsableReturnStatement errorLevel="info" />
        <NullableReturnStatement errorLevel="info" />
        <InaccessibleProperty errorLevel="info" />
        <InaccessibleMethod errorLevel="info" />
        <PropertyNotSetInConstructor errorLevel="info" />
        <UnnecessaryVarAnnotation errorLevel="info" />
        <UnusedClass errorLevel="info" />
        <UnusedMethod errorLevel="info" />
        <UnusedProperty errorLevel="info" />
        <UnusedVariable errorLevel="info" />
        <UnusedFunctionCall errorLevel="info" />
        <UnusedClosureParam errorLevel="info" />
        <UnusedParam errorLevel="info" />
        <UnusedConstructor errorLevel="info" />
        <UnusedPublicMethod errorLevel="info" />
        <UnusedProtectedMethod errorLevel="info" />
        <UnusedPrivateMethod errorLevel="info" />
        <UnusedPublicProperty errorLevel="info" />
        <UnusedProtectedProperty errorLevel="info" />
        <UnusedPrivateProperty errorLevel="info" />
        <UnusedPublicConstant errorLevel="info" />
        <UnusedProtectedConstant errorLevel="info" />
        <UnusedPrivateConstant errorLevel="info" />
        <UnusedClassConstant errorLevel="info" />
        <UnusedGlobalConstant errorLevel="info" />
        <UnusedFunctionCall errorLevel="info" />
        <UnusedMethodCall errorLevel="info" />
        <UnusedPropertyAssignment errorLevel="info" />
        <UnusedVariableAssignment errorLevel="info" />
        <UnusedClosureAssignment errorLevel="info" />
        <UnusedParamAssignment errorLevel="info" />
        <UnusedForeachValue errorLevel="info" />
        <UnusedForeachKey errorLevel="info" />
        <UnusedForValue errorLevel="info" />
        <UnusedForKey errorLevel="info" />
        <UnusedWhileValue errorLevel="info" />
        <UnusedWhileKey errorLevel="info" />
        <UnusedDoWhileValue errorLevel="info" />
        <UnusedDoWhileKey errorLevel="info" />
        <UnusedSwitchCaseValue errorLevel="info" />
        <UnusedSwitchCaseKey errorLevel="info" />
        <UnusedTryCatchValue errorLevel="info" />
        <UnusedTryCatchKey errorLevel="info" />
        <UnusedFinallyValue errorLevel="info" />
        <UnusedFinallyKey errorLevel="info" />
        <UnusedWithValue errorLevel="info" />
        <UnusedWithKey errorLevel="info" />
        <UnusedGotoValue errorLevel="info" />
        <UnusedGotoKey errorLevel="info" />
        <UnusedLabelValue errorLevel="info" />
        <UnusedLabelKey errorLevel="info" />
        <UnusedGotoValue errorLevel="info" />
        <UnusedGotoKey errorLevel="info" />
        <UnusedLabelValue errorLevel="info" />
        <UnusedLabelKey errorLevel="info" />
        <UnusedGotoValue errorLevel="info" />
        <UnusedGotoKey errorLevel="info" />
        <UnusedLabelValue errorLevel="info" />
        <UnusedLabelKey errorLevel="info" />
        <UnusedGotoValue errorLevel="info" />
        <UnusedGotoKey errorLevel="info" />
        <UnusedLabelValue errorLevel="info" />
        <UnusedLabelKey errorLevel="info" />
        <UnusedGotoValue errorLevel="info" />
        <UnusedGotoKey errorLevel="info" />
        <UnusedLabelValue errorLevel="info" />
        <UnusedLabelKey errorLevel="info" />
        <UnusedGotoValue errorLevel="info" />
        <UnusedGotoKey errorLevel="info" />
        <UnusedLabelValue errorLevel="info" />
        <UnusedLabelKey errorLevel="info" />
        <UnusedGotoValue errorLevel="info" />
        <UnusedGotoKey errorLevel="info" />
        <UnusedLabelValue errorLevel="info" />
        <UnusedLabelKey error="info" />
        <UnusedGotoValue errorLevel="info" />
        <UnusedGotoKey errorLevel="info" />
        <UnusedLabelValue errorLevel="info" />
        <UnusedLabelKey errorLevel="info" />
        <UnusedGotoValue errorLevel="info" />
        <UnusedGotoKey errorLevel="info" />
        <UnusedLabelValue errorLevel="info" />
        <UnusedLabelKey errorLevel="info" />
        <UnusedGotoValue errorLevel="info" />
        <UnusedGotoKey errorLevel="info" />
        <UnusedLabelValue errorLevel="info" />
        <UnusedLabelKey errorlevel="info" />
    </issueHandlers>
</psalm>
